avis_client/__init__.py
avis_client/api/__init__.py
avis_client/api/api_keys_api.py
avis_client/api/configuration_api.py
avis_client/api/image_api.py
avis_client/api/image_attribute_api.py
avis_client/api/image_attribute_category_api.py
avis_client/api/inspection_api.py
avis_client/api/membership_api.py
avis_client/api/metadata_api.py
avis_client/api/metadata_schema_api.py
avis_client/api/ml_api.py
avis_client/api/product_api.py
avis_client/api/product_category_api.py
avis_client/api/quality_criteria_api.py
avis_client/api/result_api.py
avis_client/api/statistics_api.py
avis_client/api/teams_api.py
avis_client/api/user_api.py
avis_client/api_client.py
avis_client/api_response.py
avis_client/configuration.py
avis_client/exceptions.py
avis_client/models/__init__.py
avis_client/models/azure_ml_inference_request.py
avis_client/models/blank_enum.py
avis_client/models/configuration_statistics.py
avis_client/models/configuration_statistics_request.py
avis_client/models/configuration_type.py
avis_client/models/configuration_type_request.py
avis_client/models/custom_user.py
avis_client/models/custom_user_request.py
avis_client/models/email_address.py
avis_client/models/format_enum.py
avis_client/models/image.py
avis_client/models/image_attribute.py
avis_client/models/image_attribute_category.py
avis_client/models/image_attribute_category_request.py
avis_client/models/image_attribute_request.py
avis_client/models/image_request.py
avis_client/models/inspection.py
avis_client/models/inspection_images_statistics.py
avis_client/models/inspection_images_statistics_request.py
avis_client/models/inspection_request.py
avis_client/models/inspection_statistics.py
avis_client/models/inspection_statistics_request.py
avis_client/models/inspection_validation_status.py
avis_client/models/membership.py
avis_client/models/membership_request.py
avis_client/models/metadata.py
avis_client/models/metadata_request.py
avis_client/models/metadata_schema.py
avis_client-0.8.0.dist-info/LICENSE
avis_client-0.8.0.dist-info/METADATA
avis_client-0.8.0.dist-info/WHEEL
avis_client-0.8.0.dist-info/RECORD
