Metadata-Version: 2.1
Name: avis_client
Version: 0.8.0
Summary: AVIS Python client
Home-page: https://docs.vu.engineering/api/clients/python/avis_client/
License: Apache-2.0
Keywords: OpenAPI,avis,api client
Author: VUEngineering
Author-email: tech@vu.engineering
Maintainer: Adriano Pagano
Maintainer-email: adriano.pagano@vu.engineering
Requires-Python: >=3.7,<4.0
Classifier: License :: OSI Approved :: Apache Software License
Classifier: Programming Language :: Python :: 3
Classifier: Programming Language :: Python :: 3.7
Classifier: Programming Language :: Python :: 3.8
Classifier: Programming Language :: Python :: 3.9
Classifier: Programming Language :: Python :: 3.10
Classifier: Programming Language :: Python :: 3.11
Requires-Dist: pydantic (>=2)
Requires-Dist: python-dateutil (>=2.8.2)
Requires-Dist: typing-extensions (>=4.7.1)
Requires-Dist: urllib3 (>=1.25.3)
Project-URL: Repository, https://github.com/vuengineering/public/
